subpubpy/__init__.py
subpubpy/abstract.py
subpubpy/core.py
subpubpy/utils.py
subpubpy-0.0.7.dist-info/LICENSE
subpubpy-0.0.7.dist-info/METADATA
subpubpy-0.0.7.dist-info/WHEEL
subpubpy-0.0.7.dist-info/top_level.txt
subpubpy-0.0.7.dist-info/RECORD
