Metadata-Version: 2.1
Name: subpubpy
Version: 0.0.7
Summary: Multithreading supported python package for publisher and subscriber model.
Home-page: https://codeart7.com
Author: Rahul Singh
Author-email: rajput.rahul8510@gmail.com
Project-URL: Home page, https://github.com/Rahul-singh98/subpubpy
Project-URL: Bug Reports, https://github.com/Rahul-singh98/subpubpy/issues
Project-URL: Feedback, https://codeart7.com/feedback
Keywords: subpubpy,setuptools,development
Classifier: Development Status :: 3 - Alpha
Classifier: Intended Audience :: Developers
Classifier: Operating System :: OS Independent
Classifier: License :: OSI Approved :: MIT License
Classifier: Programming Language :: Python :: 3
Classifier: Programming Language :: Python :: 3.8
Classifier: Programming Language :: Python :: 3.9
Classifier: Programming Language :: Python :: 3.10
Classifier: Programming Language :: Python :: 3 :: Only
Requires-Python: >=3.8, <4
License-File: LICENSE
Provides-Extra: dev
Requires-Dist: check-manifest ; extra == 'dev'
Provides-Extra: test
Requires-Dist: coverage ; extra == 'test'
